pobax/__init__.py
pobax/config.py
pobax/algos/__init__.py
pobax/algos/ppo.py
pobax/algos/transformer_xl.py
pobax/envs/__init__.py
pobax/envs/classic/__init__.py
pobax/envs/classic/pomdp.py
pobax/envs/classic/POMDP/4x3.POMDP
pobax/envs/classic/POMDP/4x3_nonterminating.POMDP
pobax/envs/classic/POMDP/cheese.95.POMDP
pobax/envs/classic/POMDP/cheese.95_nonterminating.POMDP
pobax/envs/classic/POMDP/fully_observable_tmaze2.POMDP
pobax/envs/classic/POMDP/fully_observable_tmaze5.POMDP
pobax/envs/classic/POMDP/hallway.POMDP
pobax/envs/classic/POMDP/heavenhell.POMDP
pobax/envs/classic/POMDP/network.POMDP
pobax/envs/classic/POMDP/paint.POMDP
pobax/envs/classic/POMDP/shuttle.POMDP
pobax/envs/classic/POMDP/tiger-alt-start.POMDP
pobax/envs/classic/POMDP/tmaze2.POMDP
pobax/envs/classic/POMDP/tmaze5.POMDP
pobax/envs/configs/rocksample_11_11_config.json
pobax/envs/configs/rocksample_15_15_config.json
pobax/envs/configs/rocksample_5_5_config.json
pobax/envs/configs/rocksample_7_8_config.json
pobax/envs/configs/ocean_nav/fishing_0_config.json
pobax/envs/configs/ocean_nav/fishing_1_config.json
pobax/envs/configs/ocean_nav/fishing_2_config.json
pobax/envs/configs/ocean_nav/fishing_3_config.json
pobax/envs/configs/ocean_nav/fishing_4_config.json
pobax/envs/configs/ocean_nav/fishing_5_config.json
pobax/envs/configs/ocean_nav/fishing_6_config.json
pobax/envs/configs/ocean_nav/fishing_7_config.json
pobax/envs/configs/ocean_nav/fishing_8_config.json
pobax/envs/configs/ocean_nav/task_0_config.json
pobax/envs/configs/ocean_nav/task_1_config.json
pobax/envs/configs/ocean_nav/task_2_config.json
pobax/envs/configs/ocean_nav/task_3_config.json
pobax/envs/jax/__init__.py
pobax/envs/jax/battleship.py
pobax/envs/jax/compass_world.py
pobax/envs/jax/fishing.py
pobax/envs/jax/navix_mazes.py
pobax/envs/jax/pocman.py
pobax/envs/jax/reacher_pomdp.py
pobax/envs/jax/rocksample.py
pobax/envs/jax/simple_chain.py
pobax/envs/jax/tmaze.py
pobax/envs/wrappers/__init__.py
pobax/envs/wrappers/gymnasium.py
pobax-0.0.1.dist-info/METADATA
pobax-0.0.1.dist-info/WHEEL
pobax-0.0.1.dist-info/licenses/LICENSE
pobax-0.0.1.dist-info/RECORD
