Metadata-Version: 2.4
Name: pobax
Version: 0.0.1
Summary: Reinforcement learning benchmark that tests all forms of partial observability in JAX.
Project-URL: Homepage, https://github.com/taodav/pobax
Author-email: "Ruo Yu (David) Tao" <ruoyutao@gmail.com>
License: Apache-2.0
License-File: LICENSE
Classifier: License :: OSI Approved :: Apache Software License
Classifier: Operating System :: OS Independent
Classifier: Programming Language :: Python :: 3.10
Classifier: Programming Language :: Python :: 3.11
Classifier: Programming Language :: Python :: 3.12
Classifier: Programming Language :: Python :: 3.13
Classifier: Topic :: Scientific/Engineering :: Artificial Intelligence
Requires-Python: >=3.10
Requires-Dist: brax
Requires-Dist: distrax
Requires-Dist: flax
Requires-Dist: gymnax
Requires-Dist: jax
Requires-Dist: jumanji
Requires-Dist: matplotlib
Requires-Dist: numpy
Requires-Dist: optax
Requires-Dist: pandas
Requires-Dist: seaborn
Requires-Dist: tqdm
Requires-Dist: typed-argument-parser
Provides-Extra: dev
Requires-Dist: pytest; extra == 'dev'
Provides-Extra: test
Requires-Dist: brax; extra == 'test'
Requires-Dist: chex; extra == 'test'
Requires-Dist: flax; extra == 'test'
Requires-Dist: minatar; extra == 'test'
